get_useragents/settings.py
get_useragents/useragents.py
get_useragents/data/get_useragents.json
get_useragents-1.7.dist-info/AUTHORS
get_useragents-1.7.dist-info/LICENSE
get_useragents-1.7.dist-info/METADATA
get_useragents-1.7.dist-info/WHEEL
get_useragents-1.7.dist-info/top_level.txt
get_useragents-1.7.dist-info/RECORD
