Metadata-Version: 2.1
Name: get-useragents
Version: 1.7
Summary: This library is used to make it easier for developers or users to get random user agents
Home-page: https://github.com/g4rzk/get_useragents
Download-URL: https://github.com/g4rzk/get_useragents/archive/get_useragents.tar.gz
Author: Angga Kurniawan
Author-email: g4rzkurniawan@gmail.com
License: MIT
Keywords: get_useragents,get-useragents,useragent random,get useragent,user-agent
Classifier: Development Status :: 3 - Alpha
Classifier: Intended Audience :: Developers
Classifier: Topic :: Software Development :: Build Tools
Classifier: License :: OSI Approved :: MIT License
Classifier: Programming Language :: Python :: 3.8
Classifier: Programming Language :: Python :: 3.9
Classifier: Programming Language :: Python :: 3.10
License-File: LICENSE
License-File: AUTHORS
